{"app":{"title":"Bean App","headerColor":"","textColor":"white","statusBarColor":"#ffffff","leftButton":"none","statusBar":"transparent","selfControlLoading":false,"hideAndroidBottomNavigationBar":false,"hideIOSSafeAreaBottom":true,"actionBarHidden":true,"textAlign":"center"},"debug":false,"listCSS":["assets/style.2f22a2de.css"],"listSyncJS":["assets/index.28f61cf3.module.js"],"listAsyncJS":[],"pages":["/user","/form","/dynamic-route","/about","/404"],"template":{"primaryColor":"#04bfad","prefixCurrencySymbol":false,"currencySymbol":"đ","headerLogo":""}}